mcp_hangar/__init__.py
mcp_hangar/context.py
mcp_hangar/errors.py
mcp_hangar/facade.py
mcp_hangar/fastmcp_server.py
mcp_hangar/gc.py
mcp_hangar/http_client.py
mcp_hangar/logging_config.py
mcp_hangar/metrics.py
mcp_hangar/models.py
mcp_hangar/progress.py
mcp_hangar/retry.py
mcp_hangar/stdio_client.py
mcp_hangar/application/__init__.py
mcp_hangar/application/commands/__init__.py
mcp_hangar/application/commands/auth_commands.py
mcp_hangar/application/commands/auth_handlers.py
mcp_hangar/application/commands/commands.py
mcp_hangar/application/commands/handlers.py
mcp_hangar/application/commands/load_handlers.py
mcp_hangar/application/discovery/__init__.py
mcp_hangar/application/discovery/discovery_metrics.py
mcp_hangar/application/discovery/discovery_orchestrator.py
mcp_hangar/application/discovery/lifecycle_manager.py
mcp_hangar/application/discovery/security_validator.py
mcp_hangar/application/event_handlers/__init__.py
mcp_hangar/application/event_handlers/alert_handler.py
mcp_hangar/application/event_handlers/audit_handler.py
mcp_hangar/application/event_handlers/knowledge_base_handler.py
mcp_hangar/application/event_handlers/logging_handler.py
mcp_hangar/application/event_handlers/metrics_handler.py
mcp_hangar/application/event_handlers/persistent_audit_store.py
mcp_hangar/application/event_handlers/security_handler.py
mcp_hangar/application/mcp/tooling.py
mcp_hangar/application/ports/__init__.py
mcp_hangar/application/ports/observability.py
mcp_hangar/application/queries/__init__.py
mcp_hangar/application/queries/auth_handlers.py
mcp_hangar/application/queries/auth_queries.py
mcp_hangar/application/queries/handlers.py
mcp_hangar/application/queries/queries.py
mcp_hangar/application/read_models/__init__.py
mcp_hangar/application/read_models/provider_views.py
mcp_hangar/application/sagas/__init__.py
mcp_hangar/application/sagas/group_rebalance_saga.py
mcp_hangar/application/sagas/provider_failover_saga.py
mcp_hangar/application/sagas/provider_recovery_saga.py
mcp_hangar-0.6.2.dist-info/METADATA
mcp_hangar-0.6.2.dist-info/WHEEL
mcp_hangar-0.6.2.dist-info/entry_points.txt
mcp_hangar-0.6.2.dist-info/RECORD
