Metadata-Version: 2.4
Name: mcp-hangar
Version: 0.6.2
Summary: Production-grade infrastructure for Model Context Protocol
Project-URL: Homepage, https://mcp-hangar.io
Project-URL: Documentation, https://docs.mcp-hangar.io
Project-URL: Repository, https://github.com/mapyr/mcp-hangar
Author-email: Marcin Pyrka <marcin@mcp-hangar.io>
License: MIT
Keywords: ai,infrastructure,llm,mcp,model-context-protocol
Classifier: Development Status :: 4 - Beta
Classifier: Intended Audience :: Developers
Classifier: License :: OSI Approved :: MIT License
Classifier: Programming Language :: Python :: 3.11
Classifier: Programming Language :: Python :: 3.12
Classifier: Programming Language :: Python :: 3.13
Requires-Python: >=3.11
Requires-Dist: aiosqlite>=0.19.0
Requires-Dist: cryptography>=41.0.0
Requires-Dist: docker>=7.1.0
Requires-Dist: httpx>=0.25.0
Requires-Dist: mcp>=1.0.0
Requires-Dist: prometheus-client>=0.19.0
Requires-Dist: protobuf>=6.33.5
Requires-Dist: pydantic>=2.0.0
Requires-Dist: pyjwt>=2.8.0
Requires-Dist: python-multipart>=0.0.22
Requires-Dist: pyyaml>=6.0
Requires-Dist: questionary>=2.0.0
Requires-Dist: rich>=13.0.0
Requires-Dist: structlog>=24.0.0
Requires-Dist: typer>=0.12.0
Provides-Extra: dev
Requires-Dist: hypothesis>=6.90.0; extra == 'dev'
Requires-Dist: mypy>=1.8.0; extra == 'dev'
Requires-Dist: pytest-asyncio>=0.23.0; extra == 'dev'
Requires-Dist: pytest-cov>=4.1.0; extra == 'dev'
Requires-Dist: pytest-timeout>=2.2.0; extra == 'dev'
Requires-Dist: pytest>=8.0.0; extra == 'dev'
Requires-Dist: ruff>=0.3.0; extra == 'dev'
Provides-Extra: langfuse
Requires-Dist: langfuse>=2.0.0; extra == 'langfuse'
Provides-Extra: opentelemetry
Requires-Dist: opentelemetry-api>=1.22.0; extra == 'opentelemetry'
Requires-Dist: opentelemetry-exporter-otlp>=1.22.0; extra == 'opentelemetry'
Requires-Dist: opentelemetry-sdk>=1.22.0; extra == 'opentelemetry'
Provides-Extra: postgres
Requires-Dist: asyncpg>=0.29.0; extra == 'postgres'
